iterum/__about__.py
iterum/__init__.py
iterum/_diterum.py
iterum/_helpers.py
iterum/_iterum.py
iterum/_notset.py
iterum/_option.py
iterum/_ordering.py
iterum/_seq.py
iterum/_singleton.py
iterum/_type_helpers.py
iterum/py.typed
iterum-0.2.0.dist-info/METADATA
iterum-0.2.0.dist-info/WHEEL
iterum-0.2.0.dist-info/licenses/LICENSE.txt
iterum-0.2.0.dist-info/RECORD
