Metadata-Version: 2.1
Name: iterum
Version: 0.2.0
Summary: Rusty iterators in Python.
Project-URL: Documentation, https://tjsmart.github.io/iterum
Project-URL: Source, https://github.com/tjsmart/iterum
Author-email: Tyler Smart <tjsmart@ucsc.edu>
License-Expression: MIT
License-File: LICENSE.txt
Classifier: Development Status :: 4 - Beta
Classifier: Programming Language :: Python
Classifier: Programming Language :: Python :: 3.11
Classifier: Programming Language :: Python :: Implementation :: CPython
Requires-Python: >=3.11
